{
	"name": "lsSQL",
	"properties": {
		"annotations": [],
		"type": "AzureSqlDatabase",
		"typeProperties": {
			"connectionString": "Integrated Security=False;Encrypt=True;Connection Timeout=30;Data Source=dsdrehi440.database.windows.net;Initial Catalog=dbdrehi440;User ID=drehi440",
			"password": {
				"type": "AzureKeyVaultSecret",
				"store": {
					"referenceName": "ls_kv",
					"type": "LinkedServiceReference"
				},
				"secretName": "dfkeydbsecretdrehi440"
			}
		}
	},
	"type": "Microsoft.DataFactory/factories/linkedservices"
}